yaml_to_openstep_plist/__init__.py
yaml_to_openstep_plist/converter.py
yaml_to_openstep_plist-0.2.0.dist-info/METADATA
yaml_to_openstep_plist-0.2.0.dist-info/WHEEL
yaml_to_openstep_plist-0.2.0.dist-info/licenses/LICENSE
yaml_to_openstep_plist-0.2.0.dist-info/RECORD
