Metadata-Version: 2.4
Name: yaml_to_openstep_plist
Version: 0.2.0
Summary: A Python library to convert YAML data to OpenStep plist format.
Project-URL: Homepage, https://github.com/Sandy10247/yaml_to_openstep_plist
Project-URL: Repository, https://github.com/Sandy10247/yaml_to_openstep_plist.git
Project-URL: Issues, https://github.com/Sandy10247/yaml_to_openstep_plist/issues
Author-email: Sandy10247 <sandilyakaravadi@gmail.com>
License: MIT
License-File: LICENSE
Requires-Python: >=3.6
Requires-Dist: pyyaml>=5.1
